idea/__init__.py
idea/_constants.py
idea/_go.py
idea/_idea.py
idea/_utils.py
idea_bio-0.2.6.dist-info/LICENSE
idea_bio-0.2.6.dist-info/METADATA
idea_bio-0.2.6.dist-info/WHEEL
idea_bio-0.2.6.dist-info/RECORD
