Metadata-Version: 2.1
Name: idea-bio
Version: 0.2.6
Summary: Integrated Differential Expression and Annotation
Home-page: https://github.com/noamteyssier/idea
License: MIT
Keywords: bioinformatics,differential expression,annotation,networks
Author: Noam Teyssier
Requires-Python: >=3.8,<4.0
Classifier: License :: OSI Approved :: MIT License
Classifier: Programming Language :: Python :: 3
Classifier: Programming Language :: Python :: 3.8
Classifier: Programming Language :: Python :: 3.9
Classifier: Programming Language :: Python :: 3.10
Classifier: Programming Language :: Python :: 3.11
Classifier: Programming Language :: Python :: 3.12
Classifier: Programming Language :: Python :: 3.13
Requires-Dist: beautifulsoup4 (>=4.12.2,<5.0.0)
Requires-Dist: ggetrs (>=0.1.87,<0.2.0)
Requires-Dist: matplotlib (>=3.7.2,<4.0.0)
Requires-Dist: networkx (>=3.1,<4.0)
Requires-Dist: numpy (>=1.24.0,<2.0.0)
Requires-Dist: pandas (>=2.0.3,<3.0.0)
Requires-Dist: pvsvg (>=0.1.3,<0.2.0)
Project-URL: Documentation, https://idea-bio.readthedocs.io/en/latest/usage.html
Project-URL: Repository, https://github.com/noamteyssier/idea
